pydd/__init__.py
pydd/dd.py
pydd/parser.py
pydd/pydd.py
pydmove-1.1.dist-info/LICENSE
pydmove-1.1.dist-info/METADATA
pydmove-1.1.dist-info/WHEEL
pydmove-1.1.dist-info/entry_points.txt
pydmove-1.1.dist-info/top_level.txt
pydmove-1.1.dist-info/RECORD
