Metadata-Version: 2.1
Name: pydmove
Version: 1.1
Summary: mv (using dd followed by rm) with a progressbar
Home-page: https://github.com/avivajpeyi/pydd
Author: Avi Vajpeyi
Author-email: avi.vajpeyi@gmail.com
License: MIT
Platform: UNKNOWN
Classifier: Programming Language :: Python :: 3
Classifier: License :: OSI Approved :: MIT License
Requires-Dist: tqdm (>=4.32.1)
